rhovee/__init__.py
rhovee/cv/__init__.py
rhovee/cv/calib.py
rhovee/cv/camera_intrinsics.py
rhovee/cv/laser.py
rhovee/cv/plucker.py
rhovee/cv/calib_old/__init__.py
rhovee/cv/calib_old/create_cb.py
rhovee/cv/extras/__init__.py
rhovee/genicam/__init__.py
rhovee/genicam/genicam_wrappers.py
rhovee/manifolds/SE2.py
rhovee/manifolds/SE3.py
rhovee/manifolds/SO2.py
rhovee/manifolds/SO3.py
rhovee/manifolds/__init__.py
rhovee/manifolds/utils.py
rhovee/pc/__init__.py
rhovee/pc/pc.py
rhovee/plot/__init__.py
rhovee/plot/plot2d.py
rhovee/plot/utils.py
rhovee/poseestim/__init__.py
rhovee/poseestim/rkmk.py
rhovee-0.0.32.dist-info/METADATA
rhovee-0.0.32.dist-info/WHEEL
rhovee-0.0.32.dist-info/top_level.txt
rhovee-0.0.32.dist-info/RECORD
