Metadata-Version: 2.1
Name: rhovee
Version: 0.0.32
Summary: Robotics and Computer Vision related algorithms
Author: Ola Alstad
License: UNKNOWN
Platform: UNKNOWN
Classifier: Programming Language :: Python :: 3
Classifier: Operating System :: OS Independent
Requires-Python: >=3.6
